pymssql.cpython-36m-x86_64-linux-gnu.so
_mssql.cpython-36m-x86_64-linux-gnu.so
pymssql_plus.libs/libsybdb-5fdc966a.so.5.1.0
pymssql_plus-0.1.1.dist-info/WHEEL
pymssql_plus-0.1.1.dist-info/METADATA
pymssql_plus-0.1.1.dist-info/top_level.txt
pymssql_plus-0.1.1.dist-info/RECORD
pymssql_plus-0.1.1.dist-info/LICENSE
